Workbook

Sheet Revenue
A1: Month | B1: Budget Revenue | C1: Actual Revenue | D1: Revenue Variance | E1: Revenue Variance %
A2: Jan | B2: 3000000 | C2: 2920000 | D2: =C2-B2 -> -80000 | E2: =IFERROR(D2/B2,0) -> -0.026666667
A3: Feb | B3: 3100000 | C3: 3050000 | D3: =C3-B3 -> -50000 | E3: =IFERROR(D3/B3,0) -> -0.016129032
A4: Mar | B4: 3250000 | C4: 3180000 | D4: =C4-B4 -> -70000 | E4: =IFERROR(D4/B4,0) -> -0.021538462
A5: Apr | B5: 3300000 | C5: 3270000 | D5: =C5-B5 -> -30000 | E5: =IFERROR(D5/B5,0) -> -0.0090909091
A6: May | B6: 3350000 | C6: 3310000 | D6: =C6-B6 -> -40000 | E6: =IFERROR(D6/B6,0) -> -0.011940299
A7: Jun | B7: 3400000 | C7: 3360000 | D7: =C7-B7 -> -40000 | E7: =IFERROR(D7/B7,0) -> -0.011764706
A8: Jul | B8: 3450000 | C8: 3380000 | D8: =C8-B8 -> -70000 | E8: =IFERROR(D8/B8,0) -> -0.020289855
A9: Aug | B9: 3500000 | C9: 3440000 | D9: =C9-B9 -> -60000 | E9: =IFERROR(D9/B9,0) -> -0.017142857
A10: Sep | B10: 3550000 | C10: 3490000 | D10: =C10-B10 -> -60000 | E10: =IFERROR(D10/B10,0) -> -0.016901408
A11: Oct | B11: 3600000 | C11: 3510000 | D11: =C11-B11 -> -90000 | E11: =IFERROR(D11/B11,0) -> -0.025
A12: Nov | B12: 3650000 | C12: 3590000 | D12: =C12-B12 -> -60000 | E12: =IFERROR(D12/B12,0) -> -0.016438356
A13: Dec | B13: 3750000 | C13: 3680000 | D13: =C13-B13 -> -70000 | E13: =IFERROR(D13/B13,0) -> -0.018666667

Sheet Operating Expense
A1: Month | B1: Department | C1: Budget | D1: Actual | E1: Variance | F1: Variance % | G1: Fav/UnFav | H1: Actual Cost per HC | I1: Budget Cost per HC | J1: Cost Per HC Variance | K1: Cost Per HC Variance %
A2: Jan | B2: Sales | C2: 500000 | D2: 530000 | E2: =D2-C2 -> 30000 | F2: =IFERROR(E2/C2,0) -> 0.06 | G2: =IF(E2>0, "Unfavorable","Favorable") -> Unfavorable | H2: =D2/Headcount!D2 -> 11276.596 | I2: =C2/Headcount!C2 -> 11111.111 | J2: =H2-I2 -> 165.48463 | K2: =IFERROR(J2/I2,0) -> 0.014893617
A3: Jan | B3: Marketing | C3: 350000 | D3: 388500 | E3: =D3-C3 -> 38500 | F3: =IFERROR(E3/C3,0) -> 0.11 | G3: =IF(E3>0, "Unfavorable","Favorable") -> Unfavorable | H3: =D3/Headcount!D3 -> 19425 | I3: =C3/Headcount!C3 -> 19444.444 | J3: =H3-I3 -> -19.444444 | K3: =IFERROR(J3/I3,0) -> -0.001
A4: Jan | B4: R&D | C4: 420000 | D4: 411600 | E4: =D4-C4 -> -8400 | F4: =IFERROR(E4/C4,0) -> -0.02 | G4: =IF(E4>0, "Unfavorable","Favorable") -> Favorable | H4: =D4/Headcount!D4 -> 6052.9412 | I4: =C4/Headcount!C4 -> 6000 | J4: =H4-I4 -> 52.941176 | K4: =IFERROR(J4/I4,0) -> 0.0088235294
A5: Jan | B5: G&A | C5: 220000 | D5: 204600 | E5: =D5-C5 -> -15400 | F5: =IFERROR(E5/C5,0) -> -0.07 | G5: =IF(E5>0, "Unfavorable","Favorable") -> Favorable | H5: =D5/Headcount!D5 -> 13640 | I5: =C5/Headcount!C5 -> 14666.667 | J5: =H5-I5 -> -1026.6667 | K5: =IFERROR(J5/I5,0) -> -0.07
A6: Feb | B6: Sales | C6: 500000 | D6: 530000 | E6: =D6-C6 -> 30000 | F6: =IFERROR(E6/C6,0) -> 0.06 | G6: =IF(E6>0, "Unfavorable","Favorable") -> Unfavorable | H6: =D6/Headcount!D6 -> 11276.596 | I6: =C6/Headcount!C6 -> 11111.111 | J6: =H6-I6 -> 165.48463 | K6: =IFERROR(J6/I6,0) -> 0.014893617
A7: Feb | B7: Marketing | C7: 350000 | D7: 388500 | E7: =D7-C7 -> 38500 | F7: =IFERROR(E7/C7,0) -> 0.11 | G7: =IF(E7>0, "Unfavorable","Favorable") -> Unfavorable | H7: =D7/Headcount!D7 -> 19425 | I7: =C7/Headcount!C7 -> 19444.444 | J7: =H7-I7 -> -19.444444 | K7: =IFERROR(J7/I7,0) -> -0.001
A8: Feb | B8: R&D | C8: 420000 | D8: 411600 | E8: =D8-C8 -> -8400 | F8: =IFERROR(E8/C8,0) -> -0.02 | G8: =IF(E8>0, "Unfavorable","Favorable") -> Favorable | H8: =D8/Headcount!D8 -> 6052.9412 | I8: =C8/Headcount!C8 -> 6000 | J8: =H8-I8 -> 52.941176 | K8: =IFERROR(J8/I8,0) -> 0.0088235294
A9: Feb | B9: G&A | C9: 220000 | D9: 204600 | E9: =D9-C9 -> -15400 | F9: =IFERROR(E9/C9,0) -> -0.07 | G9: =IF(E9>0, "Unfavorable","Favorable") -> Favorable | H9: =D9/Headcount!D9 -> 13640 | I9: =C9/Headcount!C9 -> 14666.667 | J9: =H9-I9 -> -1026.6667 | K9: =IFERROR(J9/I9,0) -> -0.07
A10: Mar | B10: Sales | C10: 500000 | D10: 530000 | E10: =D10-C10 -> 30000 | F10: =IFERROR(E10/C10,0) -> 0.06 | G10: =IF(E10>0, "Unfavorable","Favorable") -> Unfavorable | H10: =D10/Headcount!D10 -> 11276.596 | I10: =C10/Headcount!C10 -> 11111.111 | J10: =H10-I10 -> 165.48463 | K10: =IFERROR(J10/I10,0) -> 0.014893617
A11: Mar | B11: Marketing | C11: 350000 | D11: 388500 | E11: =D11-C11 -> 38500 | F11: =IFERROR(E11/C11,0) -> 0.11 | G11: =IF(E11>0, "Unfavorable","Favorable") -> Unfavorable | H11: =D11/Headcount!D11 -> 19425 | I11: =C11/Headcount!C11 -> 19444.444 | J11: =H11-I11 -> -19.444444 | K11: =IFERROR(J11/I11,0) -> -0.001
A12: Mar | B12: R&D | C12: 420000 | D12: 411600 | E12: =D12-C12 -> -8400 | F12: =IFERROR(E12/C12,0) -> -0.02 | G12: =IF(E12>0, "Unfavorable","Favorable") -> Favorable | H12: =D12/Headcount!D12 -> 6052.9412 | I12: =C12/Headcount!C12 -> 6000 | J12: =H12-I12 -> 52.941176 | K12: =IFERROR(J12/I12,0) -> 0.0088235294
A13: Mar | B13: G&A | C13: 220000 | D13: 204600 | E13: =D13-C13 -> -15400 | F13: =IFERROR(E13/C13,0) -> -0.07 | G13: =IF(E13>0, "Unfavorable","Favorable") -> Favorable | H13: =D13/Headcount!D13 -> 13640 | I13: =C13/Headcount!C13 -> 14666.667 | J13: =H13-I13 -> -1026.6667 | K13: =IFERROR(J13/I13,0) -> -0.07
... A49: Dec | B49: G&A | C49: 220000 | D49: 204600 | E49: =D49-C49 -> -15400 | F49: =IFERROR(E49/C49,0) -> -0.07 | G49: =IF(E49>0, "Unfavorable","Favorable") -> Favorable | H49: =D49/Headcount!D49 -> 13640 | I49: =C49/Headcount!C49 -> 14666.667 | J49: =H49-I49 -> -1026.6667 | K49: =IFERROR(J49/I49,0) -> -0.07

Sheet Headcount
A1: Month | B1: Department | C1: Budget HC | D1: Actual HC | E1: HC Variance | F1: HC Variance %
A2: Jan | B2: Sales | C2: 45 | D2: 47 | E2: =D2-C2 -> 2 | F2: =IFERROR(E2/C2,0) -> 0.044444444
A3: Jan | B3: Marketing | C3: 18 | D3: 20 | E3: =D3-C3 -> 2 | F3: =IFERROR(E3/C3,0) -> 0.11111111
A4: Jan | B4: R&D | C4: 70 | D4: 68 | E4: =D4-C4 -> -2 | F4: =IFERROR(E4/C4,0) -> -0.028571429
A5: Jan | B5: G&A | C5: 15 | D5: 15 | E5: =D5-C5 -> 0 | F5: =IFERROR(E5/C5,0) -> 0
A6: Feb | B6: Sales | C6: 45 | D6: 47 | E6: =D6-C6 -> 2 | F6: =IFERROR(E6/C6,0) -> 0.044444444
A7: Feb | B7: Marketing | C7: 18 | D7: 20 | E7: =D7-C7 -> 2 | F7: =IFERROR(E7/C7,0) -> 0.11111111
A8: Feb | B8: R&D | C8: 70 | D8: 68 | E8: =D8-C8 -> -2 | F8: =IFERROR(E8/C8,0) -> -0.028571429
A9: Feb | B9: G&A | C9: 15 | D9: 15 | E9: =D9-C9 -> 0 | F9: =IFERROR(E9/C9,0) -> 0
A10: Mar | B10: Sales | C10: 45 | D10: 47 | E10: =D10-C10 -> 2 | F10: =IFERROR(E10/C10,0) -> 0.044444444
A11: Mar | B11: Marketing | C11: 18 | D11: 20 | E11: =D11-C11 -> 2 | F11: =IFERROR(E11/C11,0) -> 0.11111111
A12: Mar | B12: R&D | C12: 70 | D12: 68 | E12: =D12-C12 -> -2 | F12: =IFERROR(E12/C12,0) -> -0.028571429
A13: Mar | B13: G&A | C13: 15 | D13: 15 | E13: =D13-C13 -> 0 | F13: =IFERROR(E13/C13,0) -> 0
... A49: Dec | B49: G&A | C49: 15 | D49: 15 | E49: =D49-C49 -> 0 | F49: =IFERROR(E49/C49,0) -> 0
A53: Marketing overspend was primarily driven by headcount growth.
A55: R&D underspend was largely driven by slower hiring.
A57: G&A savings were driven by non-payroll expense reductions rather than headcount changes.

Sheet KPI
A1: Metric | B1: Budget | C1: Actual | D1: Variance | E1: Variance% | F1: Status
A2: Revenue | B2: =SUM(Revenue!B2:B13) -> 40900000 | C2: =SUM(Revenue!C2:C13) -> 40180000 | D2: =C2-B2 -> -720000 | E2: =D2/B2 -> -0.017603912 | F2: =IFERROR(IF(D2<0,-1,1),0) -> -1
A3: OPEX | B3: =SUM('Operating Expense'!C2:C49) -> 17880000 | C3: =SUM('Operating Expense'!D2:D49) -> 18416400 | D3: =C3-B3 -> 536400 | E3: =D3/B3 -> 0.03 | F3: =IFERROR(IF(D3>0,-1,1),0) -> -1
A4: Total HC | B4: =SUM(Headcount!C2:C5) -> 148 | C4: =SUM(Headcount!D2:D5) -> 150 | D4: =C4-B4 -> 2 | E4: =D4/B4 -> 0.013513514 | F4: 0
A5: ARR Growth | B5: 0.2 | C5: 0.18 | D5: =C5-B5 -> -0.02 | E5: =D5/B5 -> -0.1 | F5: =IFERROR(IF(D5<0,-1,1),0) -> -1
A6: Gross Margin | B6: 0.78 | C6: 0.76 | D6: =C6-B6 -> -0.02 | E6: =D6/B6 -> -0.025641026 | F6: =IFERROR(IF(D6<0,-1,1),0) -> -1
A7: EBITDA Margin | B7: 0.18 | C7: 0.15 | D7: =C7-B7 -> -0.03 | E7: =D7/B7 -> -0.16666667 | F7: =IFERROR(IF(D7<0,-1,1),0) -> -1
A8: Churn Rate | B8: 0.05 | C8: 0.065 | D8: =C8-B8 -> 0.015 | E8: =D8/B8 -> 0.3 | F8: =IFERROR(IF(D8>0,-1,1),0) -> -1

Sheet Summary
B2: Department | C2: HC Variance % | E2: Department | F2: Variance % | G2: Fav/UnFav | J2: Department | K2: Cost Per HC Variance %
B3: Sales | C3: 0.044444444 | E3: Sales | F3: 0.06 | G3: Unfavorable | J3: Sales | K3: 0.014893617
B4: Marketing | C4: 0.11111111 | E4: Marketing | F4: 0.11 | G4: Unfavorable | J4: Marketing | K4: -0.001
B5: R&D | C5: -0.028571429 | E5: R&D | F5: -0.02 | G5: Favorable | J5: R&D | K5: 0.0088235294
B6: G&A | C6: 0 | E6: G&A | F6: -0.07 | G6: Favorable | J6: G&A | K6: -0.07
B11: Marketing overspend was almost entirely driven by headcount growth, while unit cost remained stable.
B13: R&D underspend was mainly attributable to slower hiring, partially offset by slightly higher per-employee costs.
B15: G&A savings were entirely driven by lower non-payroll spending rather than workforce changes.
B17: Sales overspend was primarily driven by higher headcount, with a smaller contribution from higher per-employee costs.
B21: Month | C21: Revenue Variance %
B22: Jan | C22: -0.026666667
B23: Feb | C23: -0.016129032
B24: Mar | C24: -0.021538462
B25: Apr | C25: -0.0090909091
B26: May | C26: -0.011940299
B27: Jun | C27: -0.011764706
B28: Jul | C28: -0.020289855
B29: Aug | C29: -0.017142857
B30: Sep | C30: -0.016901408
B31: Oct | C31: -0.025
B32: Nov | C32: -0.016438356
B33: Dec | C33: -0.018666667
B35: Revenue miss has remained persistent throughout the year, indicating structural weakness in demand generation rather than one-time execution issues
